{"_ts":[1483262317],"_r":{"breakdown":{"html":{"bytes":[55196],"requests":[2]},"js":{"bytes":[270421],"requests":[12]},"css":{"bytes":[213937],"requests":[4]},"image":{"bytes":[983463],"requests":[8]},"flash":{"bytes":[0],"requests":[0]},"font":{"bytes":[74530],"requests":[5]},"other":{"bytes":[2996205],"requests":[3]}},"date":[1483262317],"domElements":[239],"domInteractive":[3879],"firstPaint":[3332],"fullyLoaded":[10428],"id":["170101_X1_AF0"],"loadTime":[5938],"render":[3901],"SpeedIndex":[9910],"TTFB":[1331],"videoFrames":[[{"_t":0,"_vc":0},{"_t":3900,"_vc":2},{"_t":4000,"_vc":2},{"_t":4100,"_vc":2},{"_t":4200,"_vc":1},{"_t":4300,"_vc":0},{"_t":4500,"_vc":0},{"_t":4700,"_vc":0},{"_t":4800,"_vc":0},{"_t":5000,"_vc":1},{"_t":5200,"_vc":1},{"_t":5400,"_vc":1},{"_t":5600,"_vc":26},{"_t":5800,"_vc":26},{"_t":6000,"_vc":26},{"_t":6100,"_vc":26},{"_t":6200,"_vc":26},{"_t":6400,"_vc":24},{"_t":6600,"_vc":25},{"_t":6800,"_vc":24},{"_t":7000,"_vc":25},{"_t":7100,"_vc":25},{"_t":7300,"_vc":26},{"_t":7500,"_vc":24},{"_t":7600,"_vc":25},{"_t":7800,"_vc":26},{"_t":7900,"_vc":26},{"_t":8100,"_vc":26},{"_t":8200,"_vc":26},{"_t":8300,"_vc":26},{"_t":8500,"_vc":26},{"_t":8700,"_vc":26},{"_t":8800,"_vc":26},{"_t":9000,"_vc":27},{"_t":9100,"_vc":26},{"_t":9200,"_vc":26},{"_t":9400,"_vc":25},{"_t":9600,"_vc":26},{"_t":9800,"_vc":26},{"_t":10000,"_vc":26},{"_t":10100,"_vc":27},{"_t":10300,"_vc":27},{"_t":10500,"_vc":25},{"_t":10700,"_vc":26},{"_t":10900,"_vc":27},{"_t":11100,"_vc":74},{"_t":11200,"_vc":74},{"_t":11300,"_vc":74},{"_t":11500,"_vc":74},{"_t":11700,"_vc":74},{"_t":11900,"_vc":75},{"_t":12100,"_vc":72},{"_t":12300,"_vc":100},{"_t":12500,"_vc":100},{"_t":12600,"_vc":100}]],"visualComplete":[12288]}}